README.md
setup.py
FCrypt/BasicEncryption.py
FCrypt/FairEncryption.py
FCrypt/__init__.py
FairCrypt.egg-info/PKG-INFO
FairCrypt.egg-info/SOURCES.txt
FairCrypt.egg-info/dependency_links.txt
FairCrypt.egg-info/requires.txt
FairCrypt.egg-info/top_level.txt